{
    "description": "",
    "tags": [],
    "size": {
        "height": 2772,
        "width": 1960
    },
    "objects": [
        {
            "id": 1610796415,
            "classId": 13472086,
            "objectId": null,
            "description": "",
            "geometryType": "rectangle",
            "labelerLogin": "asanjurjo",
            "createdAt": "2024-11-21T17:07:41.402Z",
            "updatedAt": "2024-11-21T17:07:44.453Z",
            "tags": [],
            "classTitle": "OpeningBracket",
            "points": {
                "exterior": [
                    [
                        141,
                        345
                    ],
                    [
                        157,
                        620
                    ]
                ],
                "interior": []
            }
        },
        {
            "id": 1610796471,
            "classId": 13472086,
            "objectId": null,
            "description": "",
            "geometryType": "rectangle",
            "labelerLogin": "asanjurjo",
            "createdAt": "2024-11-21T17:07:54.919Z",
            "updatedAt": "2024-11-21T17:07:54.919Z",
            "tags": [],
            "classTitle": "OpeningBracket",
            "points": {
                "exterior": [
                    [
                        142,
                        978
                    ],
                    [
                        157,
                        1270
                    ]
                ],
                "interior": []
            }
        },
        {
            "id": 1610796503,
            "classId": 13472086,
            "objectId": null,
            "description": "",
            "geometryType": "rectangle",
            "labelerLogin": "asanjurjo",
            "createdAt": "2024-11-21T17:08:02.608Z",
            "updatedAt": "2024-11-21T17:08:02.608Z",
            "tags": [],
            "classTitle": "OpeningBracket",
            "points": {
                "exterior": [
                    [
                        142,
                        1614
                    ],
                    [
                        158,
                        1900
                    ]
                ],
                "interior": []
            }
        },
        {
            "id": 1610796532,
            "classId": 13472086,
            "objectId": null,
            "description": "",
            "geometryType": "rectangle",
            "labelerLogin": "asanjurjo",
            "createdAt": "2024-11-21T17:08:09.984Z",
            "updatedAt": "2024-11-21T17:08:09.984Z",
            "tags": [],
            "classTitle": "OpeningBracket",
            "points": {
                "exterior": [
                    [
                        141,
                        2260
                    ],
                    [
                        157,
                        2519
                    ]
                ],
                "interior": []
            }
        },
        {
            "id": 1610796595,
            "classId": 13461953,
            "objectId": null,
            "description": "",
            "geometryType": "rectangle",
            "labelerLogin": "asanjurjo",
            "createdAt": "2024-11-21T17:08:23.977Z",
            "updatedAt": "2024-11-21T17:08:23.977Z",
            "tags": [],
            "classTitle": "GClef",
            "points": {
                "exterior": [
                    [
                        178,
                        2228
                    ],
                    [
                        223,
                        2355
                    ]
                ],
                "interior": []
            }
        },
        {
            "id": 1610796612,
            "classId": 13472079,
            "objectId": null,
            "description": "",
            "geometryType": "rectangle",
            "labelerLogin": "asanjurjo",
            "createdAt": "2024-11-21T17:08:35.068Z",
            "updatedAt": "2024-11-21T17:08:35.068Z",
            "tags": [],
            "classTitle": "FClef",
            "points": {
                "exterior": [
                    [
                        177,
                        2455
                    ],
                    [
                        226,
                        2510
                    ]
                ],
                "interior": []
            }
        },
        {
            "id": 1610796622,
            "classId": 13472079,
            "objectId": null,
            "description": "",
            "geometryType": "rectangle",
            "labelerLogin": "asanjurjo",
            "createdAt": "2024-11-21T17:08:44.534Z",
            "updatedAt": "2024-11-21T17:08:44.534Z",
            "tags": [],
            "classTitle": "FClef",
            "points": {
                "exterior": [
                    [
                        177,
                        1835
                    ],
                    [
                        225,
                        1891
                    ]
                ],
                "interior": []
            }
        },
        {
            "id": 1610796646,
            "classId": 13461953,
            "objectId": null,
            "description": "",
            "geometryType": "rectangle",
            "labelerLogin": "asanjurjo",
            "createdAt": "2024-11-21T17:08:54.061Z",
            "updatedAt": "2024-11-21T17:08:54.061Z",
            "tags": [],
            "classTitle": "GClef",
            "points": {
                "exterior": [
                    [
                        177,
                        1582
                    ],
                    [
                        223,
                        1709
                    ]
                ],
                "interior": []
            }
        },
        {
            "id": 1610796687,
            "classId": 13461953,
            "objectId": null,
            "description": "",
            "geometryType": "rectangle",
            "labelerLogin": "asanjurjo",
            "createdAt": "2024-11-21T17:09:03.857Z",
            "updatedAt": "2024-11-21T17:09:03.857Z",
            "tags": [],
            "classTitle": "GClef",
            "points": {
                "exterior": [
                    [
                        178,
                        945
                    ],
                    [
                        223,
                        1073
                    ]
                ],
                "interior": []
            }
        },
        {
            "id": 1610796719,
            "classId": 13472079,
            "objectId": null,
            "description": "",
            "geometryType": "rectangle",
            "labelerLogin": "asanjurjo",
            "createdAt": "2024-11-21T17:09:11.869Z",
            "updatedAt": "2024-11-21T17:09:11.869Z",
            "tags": [],
            "classTitle": "FClef",
            "points": {
                "exterior": [
                    [
                        177,
                        1207
                    ],
                    [
                        226,
                        1264
                    ]
                ],
                "interior": []
            }
        },
        {
            "id": 1610796756,
            "classId": 13472079,
            "objectId": null,
            "description": "",
            "geometryType": "rectangle",
            "labelerLogin": "asanjurjo",
            "createdAt": "2024-11-21T17:09:22.187Z",
            "updatedAt": "2024-11-21T17:09:22.187Z",
            "tags": [],
            "classTitle": "FClef",
            "points": {
                "exterior": [
                    [
                        177,
                        553
                    ],
                    [
                        227,
                        609
                    ]
                ],
                "interior": []
            }
        },
        {
            "id": 1610796789,
            "classId": 13461953,
            "objectId": null,
            "description": "",
            "geometryType": "rectangle",
            "labelerLogin": "asanjurjo",
            "createdAt": "2024-11-21T17:09:31.357Z",
            "updatedAt": "2024-11-21T17:09:31.357Z",
            "tags": [],
            "classTitle": "GClef",
            "points": {
                "exterior": [
                    [
                        178,
                        313
                    ],
                    [
                        222,
                        440
                    ]
                ],
                "interior": []
            }
        },
        {
            "id": 1610796871,
            "classId": 13472091,
            "objectId": null,
            "description": "",
            "geometryType": "rectangle",
            "labelerLogin": "asanjurjo",
            "createdAt": "2024-11-21T17:09:51.233Z",
            "updatedAt": "2024-11-21T17:09:51.233Z",
            "tags": [],
            "classTitle": "Half",
            "points": {
                "exterior": [
                    [
                        492,
                        353
                    ],
                    [
                        532,
                        418
                    ]
                ],
                "interior": []
            }
        },
        {
            "id": 1610796893,
            "classId": 13472091,
            "objectId": null,
            "description": "",
            "geometryType": "rectangle",
            "labelerLogin": "asanjurjo",
            "createdAt": "2024-11-21T17:09:55.956Z",
            "updatedAt": "2024-11-21T17:09:55.956Z",
            "tags": [],
            "classTitle": "Half",
            "points": {
                "exterior": [
                    [
                        571,
                        345
                    ],
                    [
                        612,
                        417
                    ]
                ],
                "interior": []
            }
        },
        {
            "id": 1610796909,
            "classId": 13472091,
            "objectId": null,
            "description": "",
            "geometryType": "rectangle",
            "labelerLogin": "asanjurjo",
            "createdAt": "2024-11-21T17:10:07.921Z",
            "updatedAt": "2024-11-21T17:10:07.921Z",
            "tags": [],
            "classTitle": "Half",
            "points": {
                "exterior": [
                    [
                        1414,
                        340
                    ],
                    [
                        1454,
                        406
                    ]
                ],
                "interior": []
            }
        },
        {
            "id": 1610796913,
            "classId": 13472091,
            "objectId": null,
            "description": "",
            "geometryType": "rectangle",
            "labelerLogin": "asanjurjo",
            "createdAt": "2024-11-21T17:10:14.480Z",
            "updatedAt": "2024-11-21T17:10:14.480Z",
            "tags": [],
            "classTitle": "Half",
            "points": {
                "exterior": [
                    [
                        1496,
                        344
                    ],
                    [
                        1536,
                        415
                    ]
                ],
                "interior": []
            }
        },
        {
            "id": 1610796929,
            "classId": 13472091,
            "objectId": null,
            "description": "",
            "geometryType": "rectangle",
            "labelerLogin": "asanjurjo",
            "createdAt": "2024-11-21T17:10:34.093Z",
            "updatedAt": "2024-11-21T17:10:34.093Z",
            "tags": [],
            "classTitle": "Half",
            "points": {
                "exterior": [
                    [
                        505,
                        1010
                    ],
                    [
                        546,
                        1072
                    ]
                ],
                "interior": []
            }
        },
        {
            "id": 1610796932,
            "classId": 13472091,
            "objectId": null,
            "description": "",
            "geometryType": "rectangle",
            "labelerLogin": "asanjurjo",
            "createdAt": "2024-11-21T17:10:38.801Z",
            "updatedAt": "2024-11-21T17:10:38.801Z",
            "tags": [],
            "classTitle": "Half",
            "points": {
                "exterior": [
                    [
                        608,
                        995
                    ],
                    [
                        646,
                        1068
                    ]
                ],
                "interior": []
            }
        },
        {
            "id": 1610796946,
            "classId": 13472091,
            "objectId": null,
            "description": "",
            "geometryType": "rectangle",
            "labelerLogin": "asanjurjo",
            "createdAt": "2024-11-21T17:10:51.440Z",
            "updatedAt": "2024-11-21T17:10:51.440Z",
            "tags": [],
            "classTitle": "Half",
            "points": {
                "exterior": [
                    [
                        875,
                        986
                    ],
                    [
                        914,
                        1050
                    ]
                ],
                "interior": []
            }
        },
        {
            "id": 1610796948,
            "classId": 13472091,
            "objectId": null,
            "description": "",
            "geometryType": "rectangle",
            "labelerLogin": "asanjurjo",
            "createdAt": "2024-11-21T17:10:56.982Z",
            "updatedAt": "2024-11-21T17:10:56.982Z",
            "tags": [],
            "classTitle": "Half",
            "points": {
                "exterior": [
                    [
                        974,
                        968
                    ],
                    [
                        1015,
                        1045
                    ]
                ],
                "interior": []
            }
        },
        {
            "id": 1610796954,
            "classId": 13472091,
            "objectId": null,
            "description": "",
            "geometryType": "rectangle",
            "labelerLogin": "asanjurjo",
            "createdAt": "2024-11-21T17:11:04.424Z",
            "updatedAt": "2024-11-21T17:11:04.424Z",
            "tags": [],
            "classTitle": "Half",
            "points": {
                "exterior": [
                    [
                        1076,
                        977
                    ],
                    [
                        1115,
                        1059
                    ]
                ],
                "interior": []
            }
        },
        {
            "id": 1610796969,
            "classId": 13481126,
            "objectId": null,
            "description": "",
            "geometryType": "rectangle",
            "labelerLogin": "asanjurjo",
            "createdAt": "2024-11-21T17:11:20.961Z",
            "updatedAt": "2024-11-21T17:11:20.961Z",
            "tags": [],
            "classTitle": "Quarter",
            "points": {
                "exterior": [
                    [
                        1193,
                        995
                    ],
                    [
                        1235,
                        1063
                    ]
                ],
                "interior": []
            }
        },
        {
            "id": 1610796976,
            "classId": 13472091,
            "objectId": null,
            "description": "",
            "geometryType": "rectangle",
            "labelerLogin": "asanjurjo",
            "createdAt": "2024-11-21T17:11:32.760Z",
            "updatedAt": "2024-11-21T17:11:32.760Z",
            "tags": [],
            "classTitle": "Half",
            "points": {
                "exterior": [
                    [
                        1299,
                        969
                    ],
                    [
                        1338,
                        1033
                    ]
                ],
                "interior": []
            }
        },
        {
            "id": 1610796982,
            "classId": 13472091,
            "objectId": null,
            "description": "",
            "geometryType": "rectangle",
            "labelerLogin": "asanjurjo",
            "createdAt": "2024-11-21T17:11:38.290Z",
            "updatedAt": "2024-11-21T17:11:38.290Z",
            "tags": [],
            "classTitle": "Half",
            "points": {
                "exterior": [
                    [
                        1399,
                        960
                    ],
                    [
                        1439,
                        1030
                    ]
                ],
                "interior": []
            }
        },
        {
            "id": 1610796990,
            "classId": 13472091,
            "objectId": null,
            "description": "",
            "geometryType": "rectangle",
            "labelerLogin": "asanjurjo",
            "createdAt": "2024-11-21T17:11:51.332Z",
            "updatedAt": "2024-11-21T17:11:51.332Z",
            "tags": [],
            "classTitle": "Half",
            "points": {
                "exterior": [
                    [
                        270,
                        1622
                    ],
                    [
                        309,
                        1686
                    ]
                ],
                "interior": []
            }
        },
        {
            "id": 1610797014,
            "classId": 13472091,
            "objectId": null,
            "description": "",
            "geometryType": "rectangle",
            "labelerLogin": "asanjurjo",
            "createdAt": "2024-11-21T17:11:56.284Z",
            "updatedAt": "2024-11-21T17:11:56.284Z",
            "tags": [],
            "classTitle": "Half",
            "points": {
                "exterior": [
                    [
                        368,
                        1614
                    ],
                    [
                        411,
                        1683
                    ]
                ],
                "interior": []
            }
        },
        {
            "id": 1610797086,
            "classId": 13472091,
            "objectId": null,
            "description": "",
            "geometryType": "rectangle",
            "labelerLogin": "asanjurjo",
            "createdAt": "2024-11-21T17:12:13.545Z",
            "updatedAt": "2024-11-21T17:12:13.545Z",
            "tags": [],
            "classTitle": "Half",
            "points": {
                "exterior": [
                    [
                        1011,
                        1648
                    ],
                    [
                        1053,
                        1707
                    ]
                ],
                "interior": []
            }
        },
        {
            "id": 1610797120,
            "classId": 13472091,
            "objectId": null,
            "description": "",
            "geometryType": "rectangle",
            "labelerLogin": "asanjurjo",
            "createdAt": "2024-11-21T17:12:21.078Z",
            "updatedAt": "2024-11-21T17:12:21.078Z",
            "tags": [],
            "classTitle": "Half",
            "points": {
                "exterior": [
                    [
                        1113,
                        1632
                    ],
                    [
                        1153,
                        1704
                    ]
                ],
                "interior": []
            }
        },
        {
            "id": 1610797166,
            "classId": 13472091,
            "objectId": null,
            "description": "",
            "geometryType": "rectangle",
            "labelerLogin": "asanjurjo",
            "createdAt": "2024-11-21T17:12:31.848Z",
            "updatedAt": "2024-11-21T17:12:31.848Z",
            "tags": [],
            "classTitle": "Half",
            "points": {
                "exterior": [
                    [
                        1380,
                        1622
                    ],
                    [
                        1421,
                        1686
                    ]
                ],
                "interior": []
            }
        },
        {
            "id": 1610797203,
            "classId": 13472091,
            "objectId": null,
            "description": "",
            "geometryType": "rectangle",
            "labelerLogin": "asanjurjo",
            "createdAt": "2024-11-21T17:12:39.631Z",
            "updatedAt": "2024-11-21T17:12:39.631Z",
            "tags": [],
            "classTitle": "Half",
            "points": {
                "exterior": [
                    [
                        1481,
                        1605
                    ],
                    [
                        1522,
                        1683
                    ]
                ],
                "interior": []
            }
        },
        {
            "id": 1610797233,
            "classId": 13472091,
            "objectId": null,
            "description": "",
            "geometryType": "rectangle",
            "labelerLogin": "asanjurjo",
            "createdAt": "2024-11-21T17:12:47.171Z",
            "updatedAt": "2024-11-21T17:12:47.171Z",
            "tags": [],
            "classTitle": "Half",
            "points": {
                "exterior": [
                    [
                        1582,
                        1612
                    ],
                    [
                        1622,
                        1696
                    ]
                ],
                "interior": []
            }
        },
        {
            "id": 1610797266,
            "classId": 13481126,
            "objectId": null,
            "description": "",
            "geometryType": "rectangle",
            "labelerLogin": "asanjurjo",
            "createdAt": "2024-11-21T17:12:55.483Z",
            "updatedAt": "2024-11-21T17:12:55.483Z",
            "tags": [],
            "classTitle": "Quarter",
            "points": {
                "exterior": [
                    [
                        1700,
                        1632
                    ],
                    [
                        1742,
                        1700
                    ]
                ],
                "interior": []
            }
        },
        {
            "id": 1610797293,
            "classId": 13472091,
            "objectId": null,
            "description": "",
            "geometryType": "rectangle",
            "labelerLogin": "asanjurjo",
            "createdAt": "2024-11-21T17:13:11.199Z",
            "updatedAt": "2024-11-21T17:13:11.199Z",
            "tags": [],
            "classTitle": "Half",
            "points": {
                "exterior": [
                    [
                        269,
                        2251
                    ],
                    [
                        309,
                        2317
                    ]
                ],
                "interior": []
            }
        },
        {
            "id": 1610797297,
            "classId": 13472091,
            "objectId": null,
            "description": "",
            "geometryType": "rectangle",
            "labelerLogin": "asanjurjo",
            "createdAt": "2024-11-21T17:13:15.829Z",
            "updatedAt": "2024-11-21T17:13:15.829Z",
            "tags": [],
            "classTitle": "Half",
            "points": {
                "exterior": [
                    [
                        381,
                        2243
                    ],
                    [
                        423,
                        2312
                    ]
                ],
                "interior": []
            }
        },
        {
            "id": 1610797334,
            "classId": 13472091,
            "objectId": null,
            "description": "",
            "geometryType": "rectangle",
            "labelerLogin": "asanjurjo",
            "createdAt": "2024-11-21T17:13:51.243Z",
            "updatedAt": "2024-11-21T17:13:51.243Z",
            "tags": [],
            "classTitle": "Half",
            "points": {
                "exterior": [
                    [
                        879,
                        2192
                    ],
                    [
                        920,
                        2252
                    ]
                ],
                "interior": []
            }
        },
        {
            "id": 1610797342,
            "classId": 13472091,
            "objectId": null,
            "description": "",
            "geometryType": "rectangle",
            "labelerLogin": "asanjurjo",
            "createdAt": "2024-11-21T17:14:02.833Z",
            "updatedAt": "2024-11-21T17:14:02.833Z",
            "tags": [],
            "classTitle": "Half",
            "points": {
                "exterior": [
                    [
                        994,
                        2195
                    ],
                    [
                        1034,
                        2260
                    ]
                ],
                "interior": []
            }
        },
        {
            "id": 1612029585,
            "classId": 13497153,
            "objectId": null,
            "description": "",
            "geometryType": "rectangle",
            "labelerLogin": "asanjurjo",
            "createdAt": "2024-11-27T16:27:01.626Z",
            "updatedAt": "2024-11-27T16:27:05.041Z",
            "tags": [],
            "classTitle": "One",
            "points": {
                "exterior": [
                    [
                        677,
                        337
                    ],
                    [
                        717,
                        405
                    ]
                ],
                "interior": []
            }
        },
        {
            "id": 1612029601,
            "classId": 13497153,
            "objectId": null,
            "description": "",
            "geometryType": "rectangle",
            "labelerLogin": "asanjurjo",
            "createdAt": "2024-11-27T16:27:11.064Z",
            "updatedAt": "2024-11-27T16:27:11.064Z",
            "tags": [],
            "classTitle": "One",
            "points": {
                "exterior": [
                    [
                        787,
                        345
                    ],
                    [
                        829,
                        413
                    ]
                ],
                "interior": []
            }
        },
        {
            "id": 1612029608,
            "classId": 13497153,
            "objectId": null,
            "description": "",
            "geometryType": "rectangle",
            "labelerLogin": "asanjurjo",
            "createdAt": "2024-11-27T16:27:17.141Z",
            "updatedAt": "2024-11-27T16:27:17.141Z",
            "tags": [],
            "classTitle": "One",
            "points": {
                "exterior": [
                    [
                        899,
                        354
                    ],
                    [
                        940,
                        414
                    ]
                ],
                "interior": []
            }
        },
        {
            "id": 1612029629,
            "classId": 13497153,
            "objectId": null,
            "description": "",
            "geometryType": "rectangle",
            "labelerLogin": "asanjurjo",
            "createdAt": "2024-11-27T16:27:24.421Z",
            "updatedAt": "2024-11-27T16:27:28.249Z",
            "tags": [],
            "classTitle": "One",
            "points": {
                "exterior": [
                    [
                        1036,
                        362
                    ],
                    [
                        1078,
                        431
                    ]
                ],
                "interior": []
            }
        },
        {
            "id": 1612029653,
            "classId": 13497153,
            "objectId": null,
            "description": "",
            "geometryType": "rectangle",
            "labelerLogin": "asanjurjo",
            "createdAt": "2024-11-27T16:27:37.507Z",
            "updatedAt": "2024-11-27T16:27:40.956Z",
            "tags": [],
            "classTitle": "One",
            "points": {
                "exterior": [
                    [
                        1146,
                        337
                    ],
                    [
                        1188,
                        405
                    ]
                ],
                "interior": []
            }
        },
        {
            "id": 1612029667,
            "classId": 13497153,
            "objectId": null,
            "description": "",
            "geometryType": "rectangle",
            "labelerLogin": "asanjurjo",
            "createdAt": "2024-11-27T16:27:46.423Z",
            "updatedAt": "2024-11-27T16:27:46.423Z",
            "tags": [],
            "classTitle": "One",
            "points": {
                "exterior": [
                    [
                        1278,
                        328
                    ],
                    [
                        1319,
                        396
                    ]
                ],
                "interior": []
            }
        },
        {
            "id": 1612029682,
            "classId": 13497153,
            "objectId": null,
            "description": "",
            "geometryType": "rectangle",
            "labelerLogin": "asanjurjo",
            "createdAt": "2024-11-27T16:27:54.470Z",
            "updatedAt": "2024-11-27T16:27:54.470Z",
            "tags": [],
            "classTitle": "One",
            "points": {
                "exterior": [
                    [
                        1576,
                        337
                    ],
                    [
                        1617,
                        405
                    ]
                ],
                "interior": []
            }
        },
        {
            "id": 1612029691,
            "classId": 13497153,
            "objectId": null,
            "description": "",
            "geometryType": "rectangle",
            "labelerLogin": "asanjurjo",
            "createdAt": "2024-11-27T16:28:03.568Z",
            "updatedAt": "2024-11-27T16:28:07.099Z",
            "tags": [],
            "classTitle": "One",
            "points": {
                "exterior": [
                    [
                        1687,
                        328
                    ],
                    [
                        1728,
                        396
                    ]
                ],
                "interior": []
            }
        },
        {
            "id": 1612029714,
            "classId": 13497153,
            "objectId": null,
            "description": "",
            "geometryType": "rectangle",
            "labelerLogin": "asanjurjo",
            "createdAt": "2024-11-27T16:28:20.276Z",
            "updatedAt": "2024-11-27T16:28:26.008Z",
            "tags": [],
            "classTitle": "One",
            "points": {
                "exterior": [
                    [
                        266,
                        535
                    ],
                    [
                        309,
                        604
                    ]
                ],
                "interior": []
            }
        },
        {
            "id": 1612029726,
            "classId": 13497153,
            "objectId": null,
            "description": "",
            "geometryType": "rectangle",
            "labelerLogin": "asanjurjo",
            "createdAt": "2024-11-27T16:28:33.111Z",
            "updatedAt": "2024-11-27T16:28:33.111Z",
            "tags": [],
            "classTitle": "One",
            "points": {
                "exterior": [
                    [
                        379,
                        545
                    ],
                    [
                        420,
                        613
                    ]
                ],
                "interior": []
            }
        },
        {
            "id": 1612029729,
            "classId": 13497153,
            "objectId": null,
            "description": "",
            "geometryType": "rectangle",
            "labelerLogin": "asanjurjo",
            "createdAt": "2024-11-27T16:28:42.421Z",
            "updatedAt": "2024-11-27T16:28:45.468Z",
            "tags": [],
            "classTitle": "One",
            "points": {
                "exterior": [
                    [
                        488,
                        554
                    ],
                    [
                        532,
                        622
                    ]
                ],
                "interior": []
            }
        },
        {
            "id": 1612029737,
            "classId": 13497153,
            "objectId": null,
            "description": "",
            "geometryType": "rectangle",
            "labelerLogin": "asanjurjo",
            "createdAt": "2024-11-27T16:28:51.475Z",
            "updatedAt": "2024-11-27T16:28:54.475Z",
            "tags": [],
            "classTitle": "One",
            "points": {
                "exterior": [
                    [
                        677,
                        518
                    ],
                    [
                        718,
                        588
                    ]
                ],
                "interior": []
            }
        },
        {
            "id": 1612029746,
            "classId": 13497153,
            "objectId": null,
            "description": "",
            "geometryType": "rectangle",
            "labelerLogin": "asanjurjo",
            "createdAt": "2024-11-27T16:29:02.442Z",
            "updatedAt": "2024-11-27T16:29:02.442Z",
            "tags": [],
            "classTitle": "One",
            "points": {
                "exterior": [
                    [
                        786,
                        527
                    ],
                    [
                        829,
                        595
                    ]
                ],
                "interior": []
            }
        },
        {
            "id": 1612029756,
            "classId": 13497153,
            "objectId": null,
            "description": "",
            "geometryType": "rectangle",
            "labelerLogin": "asanjurjo",
            "createdAt": "2024-11-27T16:29:09.985Z",
            "updatedAt": "2024-11-27T16:29:09.985Z",
            "tags": [],
            "classTitle": "One",
            "points": {
                "exterior": [
                    [
                        898,
                        536
                    ],
                    [
                        941,
                        605
                    ]
                ],
                "interior": []
            }
        },
        {
            "id": 1612029775,
            "classId": 13497153,
            "objectId": null,
            "description": "",
            "geometryType": "rectangle",
            "labelerLogin": "asanjurjo",
            "createdAt": "2024-11-27T16:29:24.835Z",
            "updatedAt": "2024-11-27T16:29:27.873Z",
            "tags": [],
            "classTitle": "One",
            "points": {
                "exterior": [
                    [
                        731,
                        986
                    ],
                    [
                        774,
                        1055
                    ]
                ],
                "interior": []
            }
        },
        {
            "id": 1612029789,
            "classId": 13497153,
            "objectId": null,
            "description": "",
            "geometryType": "rectangle",
            "labelerLogin": "asanjurjo",
            "createdAt": "2024-11-27T16:29:35.106Z",
            "updatedAt": "2024-11-27T16:29:38.232Z",
            "tags": [],
            "classTitle": "One",
            "points": {
                "exterior": [
                    [
                        1499,
                        969
                    ],
                    [
                        1539,
                        1038
                    ]
                ],
                "interior": []
            }
        },
        {
            "id": 1612029805,
            "classId": 13497153,
            "objectId": null,
            "description": "",
            "geometryType": "rectangle",
            "labelerLogin": "asanjurjo",
            "createdAt": "2024-11-27T16:29:49.055Z",
            "updatedAt": "2024-11-27T16:29:49.055Z",
            "tags": [],
            "classTitle": "One",
            "points": {
                "exterior": [
                    [
                        1638,
                        977
                    ],
                    [
                        1679,
                        1063
                    ]
                ],
                "interior": []
            }
        },
        {
            "id": 1612029821,
            "classId": 13497153,
            "objectId": null,
            "description": "",
            "geometryType": "rectangle",
            "labelerLogin": "asanjurjo",
            "createdAt": "2024-11-27T16:30:02.994Z",
            "updatedAt": "2024-11-27T16:30:06.195Z",
            "tags": [],
            "classTitle": "One",
            "points": {
                "exterior": [
                    [
                        1638,
                        1198
                    ],
                    [
                        1680,
                        1267
                    ]
                ],
                "interior": []
            }
        },
        {
            "id": 1612029842,
            "classId": 13497153,
            "objectId": null,
            "description": "",
            "geometryType": "rectangle",
            "labelerLogin": "asanjurjo",
            "createdAt": "2024-11-27T16:30:17.380Z",
            "updatedAt": "2024-11-27T16:30:17.380Z",
            "tags": [],
            "classTitle": "One",
            "points": {
                "exterior": [
                    [
                        1074,
                        1181
                    ],
                    [
                        1115,
                        1250
                    ]
                ],
                "interior": []
            }
        },
        {
            "id": 1612029854,
            "classId": 13497153,
            "objectId": null,
            "description": "",
            "geometryType": "rectangle",
            "labelerLogin": "asanjurjo",
            "createdAt": "2024-11-27T16:30:28.908Z",
            "updatedAt": "2024-11-27T16:30:28.908Z",
            "tags": [],
            "classTitle": "One",
            "points": {
                "exterior": [
                    [
                        469,
                        1623
                    ],
                    [
                        511,
                        1691
                    ]
                ],
                "interior": []
            }
        },
        {
            "id": 1612029862,
            "classId": 13497153,
            "objectId": null,
            "description": "",
            "geometryType": "rectangle",
            "labelerLogin": "asanjurjo",
            "createdAt": "2024-11-27T16:30:37.332Z",
            "updatedAt": "2024-11-27T16:30:37.332Z",
            "tags": [],
            "classTitle": "One",
            "points": {
                "exterior": [
                    [
                        609,
                        1631
                    ],
                    [
                        650,
                        1700
                    ]
                ],
                "interior": []
            }
        },
        {
            "id": 1612029870,
            "classId": 13497153,
            "objectId": null,
            "description": "",
            "geometryType": "rectangle",
            "labelerLogin": "asanjurjo",
            "createdAt": "2024-11-27T16:30:48.295Z",
            "updatedAt": "2024-11-27T16:30:48.295Z",
            "tags": [],
            "classTitle": "One",
            "points": {
                "exterior": [
                    [
                        1239,
                        1622
                    ],
                    [
                        1281,
                        1691
                    ]
                ],
                "interior": []
            }
        },
        {
            "id": 1612029879,
            "classId": 13497153,
            "objectId": null,
            "description": "",
            "geometryType": "rectangle",
            "labelerLogin": "asanjurjo",
            "createdAt": "2024-11-27T16:31:00.399Z",
            "updatedAt": "2024-11-27T16:31:03.898Z",
            "tags": [],
            "classTitle": "One",
            "points": {
                "exterior": [
                    [
                        609,
                        1809
                    ],
                    [
                        650,
                        1878
                    ]
                ],
                "interior": []
            }
        },
        {
            "id": 1612029891,
            "classId": 13497153,
            "objectId": null,
            "description": "",
            "geometryType": "rectangle",
            "labelerLogin": "asanjurjo",
            "createdAt": "2024-11-27T16:31:13.363Z",
            "updatedAt": "2024-11-27T16:31:19.231Z",
            "tags": [],
            "classTitle": "One",
            "points": {
                "exterior": [
                    [
                        1012,
                        1810
                    ],
                    [
                        1053,
                        1879
                    ]
                ],
                "interior": []
            }
        },
        {
            "id": 1612029913,
            "classId": 13497153,
            "objectId": null,
            "description": "",
            "geometryType": "rectangle",
            "labelerLogin": "asanjurjo",
            "createdAt": "2024-11-27T16:31:35.699Z",
            "updatedAt": "2024-11-27T16:31:35.699Z",
            "tags": [],
            "classTitle": "One",
            "points": {
                "exterior": [
                    [
                        1581,
                        1810
                    ],
                    [
                        1622,
                        1879
                    ]
                ],
                "interior": []
            }
        },
        {
            "id": 1612030060,
            "classId": 13497153,
            "objectId": null,
            "description": "",
            "geometryType": "rectangle",
            "labelerLogin": "asanjurjo",
            "createdAt": "2024-11-27T16:33:18.604Z",
            "updatedAt": "2024-11-27T16:33:18.604Z",
            "tags": [],
            "classTitle": "One",
            "points": {
                "exterior": [
                    [
                        496,
                        2235
                    ],
                    [
                        538,
                        2302
                    ]
                ],
                "interior": []
            }
        },
        {
            "id": 1612030072,
            "classId": 13497153,
            "objectId": null,
            "description": "",
            "geometryType": "rectangle",
            "labelerLogin": "asanjurjo",
            "createdAt": "2024-11-27T16:33:29.271Z",
            "updatedAt": "2024-11-27T16:33:33.406Z",
            "tags": [],
            "classTitle": "One",
            "points": {
                "exterior": [
                    [
                        655,
                        2235
                    ],
                    [
                        697,
                        2346
                    ]
                ],
                "interior": []
            }
        },
        {
            "id": 1612030089,
            "classId": 13497153,
            "objectId": null,
            "description": "",
            "geometryType": "rectangle",
            "labelerLogin": "asanjurjo",
            "createdAt": "2024-11-27T16:33:41.808Z",
            "updatedAt": "2024-11-27T16:33:41.808Z",
            "tags": [],
            "classTitle": "One",
            "points": {
                "exterior": [
                    [
                        1109,
                        2209
                    ],
                    [
                        1150,
                        2269
                    ]
                ],
                "interior": []
            }
        },
        {
            "id": 1612030100,
            "classId": 13497153,
            "objectId": null,
            "description": "",
            "geometryType": "rectangle",
            "labelerLogin": "asanjurjo",
            "createdAt": "2024-11-27T16:33:50.163Z",
            "updatedAt": "2024-11-27T16:33:50.163Z",
            "tags": [],
            "classTitle": "One",
            "points": {
                "exterior": [
                    [
                        1267,
                        2200
                    ],
                    [
                        1310,
                        2260
                    ]
                ],
                "interior": []
            }
        },
        {
            "id": 1612030109,
            "classId": 13497153,
            "objectId": null,
            "description": "",
            "geometryType": "rectangle",
            "labelerLogin": "asanjurjo",
            "createdAt": "2024-11-27T16:34:02.898Z",
            "updatedAt": "2024-11-27T16:34:02.898Z",
            "tags": [],
            "classTitle": "One",
            "points": {
                "exterior": [
                    [
                        655,
                        2445
                    ],
                    [
                        697,
                        2514
                    ]
                ],
                "interior": []
            }
        },
        {
            "id": 1612030122,
            "classId": 13497153,
            "objectId": null,
            "description": "",
            "geometryType": "rectangle",
            "labelerLogin": "asanjurjo",
            "createdAt": "2024-11-27T16:34:10.902Z",
            "updatedAt": "2024-11-27T16:34:10.902Z",
            "tags": [],
            "classTitle": "One",
            "points": {
                "exterior": [
                    [
                        859,
                        2437
                    ],
                    [
                        900,
                        2505
                    ]
                ],
                "interior": []
            }
        },
        {
            "id": 1612030130,
            "classId": 13497153,
            "objectId": null,
            "description": "",
            "geometryType": "rectangle",
            "labelerLogin": "asanjurjo",
            "createdAt": "2024-11-27T16:34:19.365Z",
            "updatedAt": "2024-11-27T16:34:19.365Z",
            "tags": [],
            "classTitle": "One",
            "points": {
                "exterior": [
                    [
                        1089,
                        2420
                    ],
                    [
                        1131,
                        2488
                    ]
                ],
                "interior": []
            }
        },
        {
            "id": 1612030138,
            "classId": 13497153,
            "objectId": null,
            "description": "",
            "geometryType": "rectangle",
            "labelerLogin": "asanjurjo",
            "createdAt": "2024-11-27T16:34:28.968Z",
            "updatedAt": "2024-11-27T16:34:28.968Z",
            "tags": [],
            "classTitle": "One",
            "points": {
                "exterior": [
                    [
                        1247,
                        2428
                    ],
                    [
                        1288,
                        2497
                    ]
                ],
                "interior": []
            }
        },
        {
            "id": 1612564067,
            "classId": 13499011,
            "objectId": null,
            "description": "",
            "geometryType": "rectangle",
            "labelerLogin": "asanjurjo",
            "createdAt": "2024-11-30T12:30:37.810Z",
            "updatedAt": "2024-11-30T12:30:37.810Z",
            "tags": [],
            "classTitle": "Double",
            "points": {
                "exterior": [
                    [
                        268,
                        353
                    ],
                    [
                        309,
                        422
                    ]
                ],
                "interior": []
            }
        },
        {
            "id": 1612564070,
            "classId": 13499011,
            "objectId": null,
            "description": "",
            "geometryType": "rectangle",
            "labelerLogin": "asanjurjo",
            "createdAt": "2024-11-30T12:30:47.618Z",
            "updatedAt": "2024-11-30T12:30:47.618Z",
            "tags": [],
            "classTitle": "Double",
            "points": {
                "exterior": [
                    [
                        1035,
                        544
                    ],
                    [
                        1077,
                        613
                    ]
                ],
                "interior": []
            }
        },
        {
            "id": 1612564072,
            "classId": 13499011,
            "objectId": null,
            "description": "",
            "geometryType": "rectangle",
            "labelerLogin": "asanjurjo",
            "createdAt": "2024-11-30T12:30:58.027Z",
            "updatedAt": "2024-11-30T12:30:58.027Z",
            "tags": [],
            "classTitle": "Double",
            "points": {
                "exterior": [
                    [
                        1396,
                        518
                    ],
                    [
                        1435,
                        604
                    ]
                ],
                "interior": []
            }
        },
        {
            "id": 1612564075,
            "classId": 13499011,
            "objectId": null,
            "description": "",
            "geometryType": "rectangle",
            "labelerLogin": "asanjurjo",
            "createdAt": "2024-11-30T12:31:10.874Z",
            "updatedAt": "2024-11-30T12:31:10.874Z",
            "tags": [],
            "classTitle": "Double",
            "points": {
                "exterior": [
                    [
                        265,
                        995
                    ],
                    [
                        310,
                        1063
                    ]
                ],
                "interior": []
            }
        },
        {
            "id": 1612564106,
            "classId": 13499011,
            "objectId": null,
            "description": "",
            "geometryType": "rectangle",
            "labelerLogin": "asanjurjo",
            "createdAt": "2024-11-30T12:31:32.310Z",
            "updatedAt": "2024-11-30T12:31:32.310Z",
            "tags": [],
            "classTitle": "Double",
            "points": {
                "exterior": [
                    [
                        267,
                        1163
                    ],
                    [
                        309,
                        1249
                    ]
                ],
                "interior": []
            }
        },
        {
            "id": 1612564128,
            "classId": 13499011,
            "objectId": null,
            "description": "",
            "geometryType": "rectangle",
            "labelerLogin": "asanjurjo",
            "createdAt": "2024-11-30T12:31:39.814Z",
            "updatedAt": "2024-11-30T12:31:45.446Z",
            "tags": [],
            "classTitle": "Double",
            "points": {
                "exterior": [
                    [
                        732,
                        1189
                    ],
                    [
                        773,
                        1258
                    ]
                ],
                "interior": []
            }
        },
        {
            "id": 1612564145,
            "classId": 13499011,
            "objectId": null,
            "description": "",
            "geometryType": "rectangle",
            "labelerLogin": "asanjurjo",
            "createdAt": "2024-11-30T12:31:55.241Z",
            "updatedAt": "2024-11-30T12:31:55.241Z",
            "tags": [],
            "classTitle": "Double",
            "points": {
                "exterior": [
                    [
                        1297,
                        1197
                    ],
                    [
                        1338,
                        1266
                    ]
                ],
                "interior": []
            }
        },
        {
            "id": 1612564149,
            "classId": 13499011,
            "objectId": null,
            "description": "",
            "geometryType": "rectangle",
            "labelerLogin": "asanjurjo",
            "createdAt": "2024-11-30T12:32:06.407Z",
            "updatedAt": "2024-11-30T12:32:06.407Z",
            "tags": [],
            "classTitle": "Double",
            "points": {
                "exterior": [
                    [
                        795,
                        1597
                    ],
                    [
                        836,
                        1682
                    ]
                ],
                "interior": []
            }
        },
        {
            "id": 1612564174,
            "classId": 13499011,
            "objectId": null,
            "description": "",
            "geometryType": "rectangle",
            "labelerLogin": "asanjurjo",
            "createdAt": "2024-11-30T12:32:18.931Z",
            "updatedAt": "2024-11-30T12:32:18.931Z",
            "tags": [],
            "classTitle": "Double",
            "points": {
                "exterior": [
                    [
                        266,
                        1818
                    ],
                    [
                        309,
                        1887
                    ]
                ],
                "interior": []
            }
        },
        {
            "id": 1612564176,
            "classId": 13499011,
            "objectId": null,
            "description": "",
            "geometryType": "rectangle",
            "labelerLogin": "asanjurjo",
            "createdAt": "2024-11-30T12:32:27.682Z",
            "updatedAt": "2024-11-30T12:32:30.728Z",
            "tags": [],
            "classTitle": "Double",
            "points": {
                "exterior": [
                    [
                        774,
                        1800
                    ],
                    [
                        816,
                        1868
                    ]
                ],
                "interior": []
            }
        },
        {
            "id": 1612564198,
            "classId": 13499011,
            "objectId": null,
            "description": "",
            "geometryType": "rectangle",
            "labelerLogin": "asanjurjo",
            "createdAt": "2024-11-30T12:32:36.418Z",
            "updatedAt": "2024-11-30T12:32:36.418Z",
            "tags": [],
            "classTitle": "Double",
            "points": {
                "exterior": [
                    [
                        1239,
                        1818
                    ],
                    [
                        1281,
                        1887
                    ]
                ],
                "interior": []
            }
        },
        {
            "id": 1612564244,
            "classId": 13499011,
            "objectId": null,
            "description": "",
            "geometryType": "rectangle",
            "labelerLogin": "asanjurjo",
            "createdAt": "2024-11-30T12:32:53.628Z",
            "updatedAt": "2024-11-30T12:32:59.472Z",
            "tags": [],
            "classTitle": "Double",
            "points": {
                "exterior": [
                    [
                        860,
                        2268
                    ],
                    [
                        899,
                        2337
                    ]
                ],
                "interior": []
            }
        },
        {
            "id": 1612564247,
            "classId": 13499011,
            "objectId": null,
            "description": "",
            "geometryType": "rectangle",
            "labelerLogin": "asanjurjo",
            "createdAt": "2024-11-30T12:33:08.153Z",
            "updatedAt": "2024-11-30T12:33:11.497Z",
            "tags": [],
            "classTitle": "Double",
            "points": {
                "exterior": [
                    [
                        1432,
                        2251
                    ],
                    [
                        1472,
                        2358
                    ]
                ],
                "interior": []
            }
        },
        {
            "id": 1612564250,
            "classId": 13499011,
            "objectId": null,
            "description": "",
            "geometryType": "rectangle",
            "labelerLogin": "asanjurjo",
            "createdAt": "2024-11-30T12:33:23.500Z",
            "updatedAt": "2024-11-30T12:33:23.500Z",
            "tags": [],
            "classTitle": "Double",
            "points": {
                "exterior": [
                    [
                        1432,
                        2462
                    ],
                    [
                        1472,
                        2531
                    ]
                ],
                "interior": []
            }
        },
        {
            "id": 1612564298,
            "classId": 13499011,
            "objectId": null,
            "description": "",
            "geometryType": "rectangle",
            "labelerLogin": "asanjurjo",
            "createdAt": "2024-11-30T12:33:40.321Z",
            "updatedAt": "2024-11-30T12:33:40.321Z",
            "tags": [],
            "classTitle": "Double",
            "points": {
                "exterior": [
                    [
                        266,
                        2444
                    ],
                    [
                        309,
                        2514
                    ]
                ],
                "interior": []
            }
        },
        {
            "id": 1613214131,
            "classId": 13516152,
            "objectId": null,
            "description": "",
            "geometryType": "rectangle",
            "labelerLogin": "asanjurjo",
            "createdAt": "2024-12-04T17:00:53.416Z",
            "updatedAt": "2024-12-04T17:00:53.416Z",
            "tags": [],
            "classTitle": "RestOne",
            "points": {
                "exterior": [
                    [
                        1267,
                        2302
                    ],
                    [
                        1284,
                        2354
                    ]
                ],
                "interior": []
            }
        }
    ]
}